ascii_art.py
formatters.py
system_info.py
themes.py
vfetch.py
vfetch-0.1.0.dist-info/licenses/LICENSE
vfetch-0.1.0.dist-info/METADATA
vfetch-0.1.0.dist-info/WHEEL
vfetch-0.1.0.dist-info/entry_points.txt
vfetch-0.1.0.dist-info/top_level.txt
vfetch-0.1.0.dist-info/RECORD
