Metadata-Version: 2.4
Name: vfetch
Version: 0.1.0
Summary: A beautiful system information display tool with stunning visuals
Home-page: https://github.com/yourusername/vfetch
Author: YourName
Author-email: Your Name <your.email@example.com>
License: MIT
Project-URL: Homepage, https://github.com/yourusername/vfetch
Project-URL: Bug Tracker, https://github.com/yourusername/vfetch/issues
Project-URL: Source, https://github.com/yourusername/vfetch
Keywords: system-info,fetch,monitoring,cli,terminal,ascii-art
Classifier: Development Status :: 4 - Beta
Classifier: Environment :: Console
Classifier: Intended Audience :: Developers
Classifier: Intended Audience :: System Administrators
Classifier: License :: OSI Approved :: MIT License
Classifier: Operating System :: OS Independent
Classifier: Programming Language :: Python :: 3
Classifier: Programming Language :: Python :: 3.6
Classifier: Programming Language :: Python :: 3.7
Classifier: Programming Language :: Python :: 3.8
Classifier: Programming Language :: Python :: 3.9
Classifier: Programming Language :: Python :: 3.10
Classifier: Programming Language :: Python :: 3.11
Classifier: Topic :: System :: Monitoring
Classifier: Topic :: Utilities
Requires-Python: >=3.7
License-File: LICENSE
Requires-Dist: build>=1.1.1
Requires-Dist: psutil>=5.9.0
Requires-Dist: rich>=12.2.0
Requires-Dist: setuptools>=68.0.0
Requires-Dist: twine>=4.0.2
Dynamic: author
Dynamic: home-page
Dynamic: license-file
Dynamic: requires-python
